git_deployer/__init__.py
git_deployer/__main__.py
git_deployer/configutils.py
git_deployer/gitdeploy.py
git_deployer/gitutils.py
git_deployer/pathutils.py
git_deployer-0.1.0.dist-info/licenses/LICENSE
git_deployer-0.1.0.dist-info/METADATA
git_deployer-0.1.0.dist-info/WHEEL
git_deployer-0.1.0.dist-info/entry_points.txt
git_deployer-0.1.0.dist-info/top_level.txt
git_deployer-0.1.0.dist-info/RECORD
