Metadata-Version: 2.4
Name: git-deployer
Version: 0.1.0
Summary: Deploy your local folder to Git with one command
Author-email: Vitaly <optinsoft@gmail.com>
License-Expression: MIT
Project-URL: Homepage, https://github.com/optinsoft/git-deployer
Project-URL: Tracker, https://github.com/optinsoft/git-deployer/issues
Project-URL: Source, https://github.com/optinsoft/git-deployer
Keywords: git,deploy,python
Classifier: Programming Language :: Python :: 3
Classifier: Operating System :: OS Independent
Requires-Python: >=3.9
License-File: LICENSE
Requires-Dist: PyYAML>=6.0.1
Dynamic: license-file
